{
  "version": "5.11.3",
  "flags": {},
  "shapes": [
    {
      "label": "car",
      "points": [
        [
          176.17,
          254.02
        ]
      ],
      "group_id": null,
      "description": "",
      "shape_type": "point",
      "flags": {},
      "mask": null
    },
    {
      "label": "car",
      "points": [
        [
          285.63,
          170.57
        ]
      ],
      "group_id": null,
      "description": "",
      "shape_type": "point",
      "flags": {},
      "mask": null
    },
    {
      "label": "car",
      "points": [
        [
          317.25,
          129.65
        ]
      ],
      "group_id": null,
      "description": "",
      "shape_type": "point",
      "flags": {},
      "mask": null
    },
    {
      "label": "car",
      "points": [
        [
          385.91,
          124.47
        ]
      ],
      "group_id": null,
      "description": "",
      "shape_type": "point",
      "flags": {},
      "mask": null
    },
    {
      "label": "car",
      "points": [
        [
          218.42,
          93.34
        ]
      ],
      "group_id": null,
      "description": "",
      "shape_type": "point",
      "flags": {},
      "mask": null
    },
    {
      "label": "motorbike",
      "points": [
        [
          112.74,
          101.27
        ]
      ],
      "group_id": null,
      "description": "",
      "shape_type": "point",
      "flags": {},
      "mask": null
    },
    {
      "label": "motorbike",
      "points": [
        [
          343.57,
          188.3
        ]
      ],
      "group_id": null,
      "description": "",
      "shape_type": "point",
      "flags": {},
      "mask": null
    },
    {
      "label": "motorbike",
      "points": [
        [
          268.38,
          268.62
        ]
      ],
      "group_id": null,
      "description": "",
      "shape_type": "point",
      "flags": {},
      "mask": null
    },
    {
      "label": "car",
      "points": [
        [
          72.23,
          72.97
        ]
      ],
      "group_id": null,
      "description": "",
      "shape_type": "point",
      "flags": {},
      "mask": null
    },
    {
      "label": "car",
      "points": [
        [
          256.5,
          103.15
        ]
      ],
      "group_id": null,
      "description": "",
      "shape_type": "point",
      "flags": {},
      "mask": null
    },
    {
      "label": "motorbike",
      "points": [
        [
          40.83,
          144.52
        ]
      ],
      "group_id": null,
      "description": "",
      "shape_type": "point",
      "flags": {},
      "mask": null
    },
    {
      "label": "car",
      "points": [
        [
          203.81,
          103.21
        ]
      ],
      "group_id": null,
      "description": "",
      "shape_type": "point",
      "flags": {},
      "mask": null
    },
    {
      "label": "motorbike",
      "points": [
        [
          314.96,
          193.51
        ]
      ],
      "group_id": null,
      "description": "",
      "shape_type": "point",
      "flags": {},
      "mask": null
    },
    {
      "label": "motorbike",
      "points": [
        [
          368.19,
          173.77
        ]
      ],
      "group_id": null,
      "description": "",
      "shape_type": "point",
      "flags": {},
      "mask": null
    },
    {
      "label": "motorbike",
      "points": [
        [
          192.72,
          123.74
        ]
      ],
      "group_id": null,
      "description": "",
      "shape_type": "point",
      "flags": {},
      "mask": null
    },
    {
      "label": "motorbike",
      "points": [
        [
          319.01,
          244.52
        ]
      ],
      "group_id": null,
      "description": "",
      "shape_type": "point",
      "flags": {},
      "mask": null
    },
    {
      "label": "motorbike",
      "points": [
        [
          360.53,
          143.39
        ]
      ],
      "group_id": null,
      "description": "",
      "shape_type": "point",
      "flags": {},
      "mask": null
    },
    {
      "label": "motorbike",
      "points": [
        [
          145.66,
          67.74
        ]
      ],
      "group_id": null,
      "description": "",
      "shape_type": "point",
      "flags": {},
      "mask": null
    },
    {
      "label": "motorbike",
      "points": [
        [
          348.8,
          269.27
        ]
      ],
      "group_id": null,
      "description": "",
      "shape_type": "point",
      "flags": {},
      "mask": null
    },
    {
      "label": "motorbike",
      "points": [
        [
          394.71,
          151.09
        ]
      ],
      "group_id": null,
      "description": "",
      "shape_type": "point",
      "flags": {},
      "mask": null
    },
    {
      "label": "motorbike",
      "points": [
        [
          483.1,
          153.38
        ]
      ],
      "group_id": null,
      "description": "",
      "shape_type": "point",
      "flags": {},
      "mask": null
    },
    {
      "label": "motorbike",
      "points": [
        [
          167.57,
          119.24
        ]
      ],
      "group_id": null,
      "description": "",
      "shape_type": "point",
      "flags": {},
      "mask": null
    },
    {
      "label": "motorbike",
      "points": [
        [
          143.77,
          105.36
        ]
      ],
      "group_id": null,
      "description": "",
      "shape_type": "point",
      "flags": {},
      "mask": null
    },
    {
      "label": "motorbike",
      "points": [
        [
          440.55,
          164.37
        ]
      ],
      "group_id": null,
      "description": "",
      "shape_type": "point",
      "flags": {},
      "mask": null
    },
    {
      "label": "motorbike",
      "points": [
        [
          304.24,
          280.2
        ]
      ],
      "group_id": null,
      "description": "",
      "shape_type": "point",
      "flags": {},
      "mask": null
    },
    {
      "label": "motorbike",
      "points": [
        [
          452.17,
          105.75
        ]
      ],
      "group_id": null,
      "description": "",
      "shape_type": "point",
      "flags": {},
      "mask": null
    },
    {
      "label": "motorbike",
      "points": [
        [
          448.61,
          118.17
        ]
      ],
      "group_id": null,
      "description": "",
      "shape_type": "point",
      "flags": {},
      "mask": null
    },
    {
      "label": "motorbike",
      "points": [
        [
          468.81,
          135.11
        ]
      ],
      "group_id": null,
      "description": "",
      "shape_type": "point",
      "flags": {},
      "mask": null
    },
    {
      "label": "motorbike",
      "points": [
        [
          405.29,
          109.69
        ]
      ],
      "group_id": null,
      "description": "",
      "shape_type": "point",
      "flags": {},
      "mask": null
    },
    {
      "label": "motorbike",
      "points": [
        [
          417.2,
          135.14
        ]
      ],
      "group_id": null,
      "description": "",
      "shape_type": "point",
      "flags": {},
      "mask": null
    },
    {
      "label": "motorbike",
      "points": [
        [
          136.73,
          87.46
        ]
      ],
      "group_id": null,
      "description": "",
      "shape_type": "point",
      "flags": {},
      "mask": null
    },
    {
      "label": "motorbike",
      "points": [
        [
          249.54,
          127.67
        ]
      ],
      "group_id": null,
      "description": "",
      "shape_type": "point",
      "flags": {},
      "mask": null
    }
  ],
  "imagePath": "20251118_170236_016.jpg",
  "imageData": null,
  "imageHeight": 294,
  "imageWidth": 518
}