{
  "version": "5.11.3",
  "flags": {},
  "shapes": [
    {
      "label": "car",
      "points": [
        [
          61.47,
          211.85
        ]
      ],
      "group_id": null,
      "description": "",
      "shape_type": "point",
      "flags": {},
      "mask": null
    },
    {
      "label": "car",
      "points": [
        [
          415.48,
          85.89
        ]
      ],
      "group_id": null,
      "description": "",
      "shape_type": "point",
      "flags": {},
      "mask": null
    },
    {
      "label": "motorbike",
      "points": [
        [
          165.6,
          135.69
        ]
      ],
      "group_id": null,
      "description": "",
      "shape_type": "point",
      "flags": {},
      "mask": null
    },
    {
      "label": "motorbike",
      "points": [
        [
          127.43,
          160.4
        ]
      ],
      "group_id": null,
      "description": "",
      "shape_type": "point",
      "flags": {},
      "mask": null
    },
    {
      "label": "car",
      "points": [
        [
          51.63,
          101.32
        ]
      ],
      "group_id": null,
      "description": "",
      "shape_type": "point",
      "flags": {},
      "mask": null
    },
    {
      "label": "motorbike",
      "points": [
        [
          400.53,
          167.66
        ]
      ],
      "group_id": null,
      "description": "",
      "shape_type": "point",
      "flags": {},
      "mask": null
    },
    {
      "label": "motorbike",
      "points": [
        [
          465.47,
          210.89
        ]
      ],
      "group_id": null,
      "description": "",
      "shape_type": "point",
      "flags": {},
      "mask": null
    },
    {
      "label": "car",
      "points": [
        [
          484.37,
          54.57
        ]
      ],
      "group_id": null,
      "description": "",
      "shape_type": "point",
      "flags": {},
      "mask": null
    },
    {
      "label": "motorbike",
      "points": [
        [
          43.51,
          174.61
        ]
      ],
      "group_id": null,
      "description": "",
      "shape_type": "point",
      "flags": {},
      "mask": null
    },
    {
      "label": "motorbike",
      "points": [
        [
          284.93,
          102.44
        ]
      ],
      "group_id": null,
      "description": "",
      "shape_type": "point",
      "flags": {},
      "mask": null
    },
    {
      "label": "car",
      "points": [
        [
          449.06,
          56.61
        ]
      ],
      "group_id": null,
      "description": "",
      "shape_type": "point",
      "flags": {},
      "mask": null
    },
    {
      "label": "motorbike",
      "points": [
        [
          381.05,
          88.32
        ]
      ],
      "group_id": null,
      "description": "",
      "shape_type": "point",
      "flags": {},
      "mask": null
    },
    {
      "label": "motorbike",
      "points": [
        [
          392.02,
          131.83
        ]
      ],
      "group_id": null,
      "description": "",
      "shape_type": "point",
      "flags": {},
      "mask": null
    },
    {
      "label": "motorbike",
      "points": [
        [
          350.55,
          94.08
        ]
      ],
      "group_id": null,
      "description": "",
      "shape_type": "point",
      "flags": {},
      "mask": null
    },
    {
      "label": "car",
      "points": [
        [
          23.45,
          91.35
        ]
      ],
      "group_id": null,
      "description": "",
      "shape_type": "point",
      "flags": {},
      "mask": null
    },
    {
      "label": "motorbike",
      "points": [
        [
          209.86,
          120.16
        ]
      ],
      "group_id": null,
      "description": "",
      "shape_type": "point",
      "flags": {},
      "mask": null
    },
    {
      "label": "car",
      "points": [
        [
          501.12,
          40.0
        ]
      ],
      "group_id": null,
      "description": "",
      "shape_type": "point",
      "flags": {},
      "mask": null
    },
    {
      "label": "motorbike",
      "points": [
        [
          41.17,
          111.03
        ]
      ],
      "group_id": null,
      "description": "",
      "shape_type": "point",
      "flags": {},
      "mask": null
    },
    {
      "label": "motorbike",
      "points": [
        [
          25.61,
          117.38
        ]
      ],
      "group_id": null,
      "description": "",
      "shape_type": "point",
      "flags": {},
      "mask": null
    },
    {
      "label": "motorbike",
      "points": [
        [
          434.36,
          69.44
        ]
      ],
      "group_id": null,
      "description": "",
      "shape_type": "point",
      "flags": {},
      "mask": null
    },
    {
      "label": "motorbike",
      "points": [
        [
          368.29,
          69.0
        ]
      ],
      "group_id": null,
      "description": "",
      "shape_type": "point",
      "flags": {},
      "mask": null
    },
    {
      "label": "motorbike",
      "points": [
        [
          228.29,
          111.3
        ]
      ],
      "group_id": null,
      "description": "",
      "shape_type": "point",
      "flags": {},
      "mask": null
    },
    {
      "label": "motorbike",
      "points": [
        [
          15.24,
          109.88
        ]
      ],
      "group_id": null,
      "description": "",
      "shape_type": "point",
      "flags": {},
      "mask": null
    }
  ],
  "imagePath": "20251117_154001_061.jpg",
  "imageData": null,
  "imageHeight": 294,
  "imageWidth": 518
}