{
  "version": "5.11.3",
  "flags": {},
  "shapes": [
    {
      "label": "car",
      "points": [
        [
          234.91,
          145.88
        ]
      ],
      "group_id": null,
      "description": "",
      "shape_type": "point",
      "flags": {},
      "mask": null
    },
    {
      "label": "car",
      "points": [
        [
          188.48,
          129.99
        ]
      ],
      "group_id": null,
      "description": "",
      "shape_type": "point",
      "flags": {},
      "mask": null
    },
    {
      "label": "car",
      "points": [
        [
          46.47,
          180.32
        ]
      ],
      "group_id": null,
      "description": "",
      "shape_type": "point",
      "flags": {},
      "mask": null
    },
    {
      "label": "car",
      "points": [
        [
          399.73,
          91.39
        ]
      ],
      "group_id": null,
      "description": "",
      "shape_type": "point",
      "flags": {},
      "mask": null
    },
    {
      "label": "motorbike",
      "points": [
        [
          131.54,
          141.01
        ]
      ],
      "group_id": null,
      "description": "",
      "shape_type": "point",
      "flags": {},
      "mask": null
    },
    {
      "label": "car",
      "points": [
        [
          448.43,
          68.82
        ]
      ],
      "group_id": null,
      "description": "",
      "shape_type": "point",
      "flags": {},
      "mask": null
    },
    {
      "label": "car",
      "points": [
        [
          39.16,
          103.03
        ]
      ],
      "group_id": null,
      "description": "",
      "shape_type": "point",
      "flags": {},
      "mask": null
    },
    {
      "label": "car",
      "points": [
        [
          10.59,
          238.48
        ]
      ],
      "group_id": null,
      "description": "",
      "shape_type": "point",
      "flags": {},
      "mask": null
    },
    {
      "label": "car",
      "points": [
        [
          379.68,
          77.27
        ]
      ],
      "group_id": null,
      "description": "",
      "shape_type": "point",
      "flags": {},
      "mask": null
    },
    {
      "label": "motorbike",
      "points": [
        [
          314.36,
          132.09
        ]
      ],
      "group_id": null,
      "description": "",
      "shape_type": "point",
      "flags": {},
      "mask": null
    },
    {
      "label": "car",
      "points": [
        [
          478.64,
          46.54
        ]
      ],
      "group_id": null,
      "description": "",
      "shape_type": "point",
      "flags": {},
      "mask": null
    },
    {
      "label": "car",
      "points": [
        [
          502.13,
          49.38
        ]
      ],
      "group_id": null,
      "description": "",
      "shape_type": "point",
      "flags": {},
      "mask": null
    },
    {
      "label": "car",
      "points": [
        [
          441.91,
          57.73
        ]
      ],
      "group_id": null,
      "description": "",
      "shape_type": "point",
      "flags": {},
      "mask": null
    },
    {
      "label": "motorbike",
      "points": [
        [
          336.25,
          86.25
        ]
      ],
      "group_id": null,
      "description": "",
      "shape_type": "point",
      "flags": {},
      "mask": null
    },
    {
      "label": "car",
      "points": [
        [
          7.45,
          112.15
        ]
      ],
      "group_id": null,
      "description": "",
      "shape_type": "point",
      "flags": {},
      "mask": null
    },
    {
      "label": "motorbike",
      "points": [
        [
          372.88,
          126.48
        ]
      ],
      "group_id": null,
      "description": "",
      "shape_type": "point",
      "flags": {},
      "mask": null
    },
    {
      "label": "motorbike",
      "points": [
        [
          300.54,
          98.32
        ]
      ],
      "group_id": null,
      "description": "",
      "shape_type": "point",
      "flags": {},
      "mask": null
    },
    {
      "label": "motorbike",
      "points": [
        [
          344.18,
          71.05
        ]
      ],
      "group_id": null,
      "description": "",
      "shape_type": "point",
      "flags": {},
      "mask": null
    },
    {
      "label": "motorbike",
      "points": [
        [
          287.04,
          88.63
        ]
      ],
      "group_id": null,
      "description": "",
      "shape_type": "point",
      "flags": {},
      "mask": null
    },
    {
      "label": "motorbike",
      "points": [
        [
          311.65,
          89.06
        ]
      ],
      "group_id": null,
      "description": "",
      "shape_type": "point",
      "flags": {},
      "mask": null
    },
    {
      "label": "motorbike",
      "points": [
        [
          167.54,
          111.57
        ]
      ],
      "group_id": null,
      "description": "",
      "shape_type": "point",
      "flags": {},
      "mask": null
    },
    {
      "label": "motorbike",
      "points": [
        [
          217.15,
          97.3
        ]
      ],
      "group_id": null,
      "description": "",
      "shape_type": "point",
      "flags": {},
      "mask": null
    },
    {
      "label": "motorbike",
      "points": [
        [
          267.15,
          101.79
        ]
      ],
      "group_id": null,
      "description": "",
      "shape_type": "point",
      "flags": {},
      "mask": null
    }
  ],
  "imagePath": "20251117_153733_046.jpg",
  "imageData": null,
  "imageHeight": 294,
  "imageWidth": 518
}