{
  "version": "5.11.3",
  "flags": {},
  "shapes": [
    {
      "label": "motorbike",
      "points": [
        [
          86.99,
          158.28
        ]
      ],
      "group_id": null,
      "description": "",
      "shape_type": "point",
      "flags": {},
      "mask": null
    },
    {
      "label": "car",
      "points": [
        [
          139.55,
          117.93
        ]
      ],
      "group_id": null,
      "description": "",
      "shape_type": "point",
      "flags": {},
      "mask": null
    },
    {
      "label": "car",
      "points": [
        [
          135.6,
          92.16
        ]
      ],
      "group_id": null,
      "description": "",
      "shape_type": "point",
      "flags": {},
      "mask": null
    },
    {
      "label": "motorbike",
      "points": [
        [
          162.26,
          100.58
        ]
      ],
      "group_id": null,
      "description": "",
      "shape_type": "point",
      "flags": {},
      "mask": null
    }
  ],
  "imagePath": "20251118_170337_022.jpg",
  "imageData": null,
  "imageHeight": 294,
  "imageWidth": 518
}