{
  "version": "5.11.3",
  "flags": {},
  "shapes": [
    {
      "label": "car",
      "points": [
        [
          243.94,
          60.04
        ]
      ],
      "group_id": null,
      "description": "",
      "shape_type": "point",
      "flags": {},
      "mask": null
    },
    {
      "label": "car",
      "points": [
        [
          178.91,
          63.96
        ]
      ],
      "group_id": null,
      "description": "",
      "shape_type": "point",
      "flags": {},
      "mask": null
    },
    {
      "label": "car",
      "points": [
        [
          162.48,
          66.39
        ]
      ],
      "group_id": null,
      "description": "",
      "shape_type": "point",
      "flags": {},
      "mask": null
    },
    {
      "label": "car",
      "points": [
        [
          141.85,
          68.77
        ]
      ],
      "group_id": null,
      "description": "",
      "shape_type": "point",
      "flags": {},
      "mask": null
    },
    {
      "label": "car",
      "points": [
        [
          126.19,
          77.13
        ]
      ],
      "group_id": null,
      "description": "",
      "shape_type": "point",
      "flags": {},
      "mask": null
    },
    {
      "label": "car",
      "points": [
        [
          369.19,
          80.16
        ]
      ],
      "group_id": null,
      "description": "",
      "shape_type": "point",
      "flags": {},
      "mask": null
    },
    {
      "label": "motorbike",
      "points": [
        [
          320.73,
          80.57
        ]
      ],
      "group_id": null,
      "description": "",
      "shape_type": "point",
      "flags": {},
      "mask": null
    },
    {
      "label": "motorbike",
      "points": [
        [
          81.46,
          81.32
        ]
      ],
      "group_id": null,
      "description": "",
      "shape_type": "point",
      "flags": {},
      "mask": null
    },
    {
      "label": "motorbike",
      "points": [
        [
          419.27,
          81.37
        ]
      ],
      "group_id": null,
      "description": "",
      "shape_type": "point",
      "flags": {},
      "mask": null
    },
    {
      "label": "motorbike",
      "points": [
        [
          109.22,
          81.49
        ]
      ],
      "group_id": null,
      "description": "",
      "shape_type": "point",
      "flags": {},
      "mask": null
    },
    {
      "label": "truck",
      "points": [
        [
          183.06,
          83.35
        ]
      ],
      "group_id": null,
      "description": "",
      "shape_type": "point",
      "flags": {},
      "mask": null
    },
    {
      "label": "motorbike",
      "points": [
        [
          120.0,
          83.9
        ]
      ],
      "group_id": null,
      "description": "",
      "shape_type": "point",
      "flags": {},
      "mask": null
    },
    {
      "label": "motorbike",
      "points": [
        [
          201.47,
          84.01
        ]
      ],
      "group_id": null,
      "description": "",
      "shape_type": "point",
      "flags": {},
      "mask": null
    },
    {
      "label": "motorbike",
      "points": [
        [
          149.98,
          86.44
        ]
      ],
      "group_id": null,
      "description": "",
      "shape_type": "point",
      "flags": {},
      "mask": null
    },
    {
      "label": "car",
      "points": [
        [
          497.97,
          89.98
        ]
      ],
      "group_id": null,
      "description": "",
      "shape_type": "point",
      "flags": {},
      "mask": null
    },
    {
      "label": "coach",
      "points": [
        [
          455.7,
          90.15
        ]
      ],
      "group_id": null,
      "description": "",
      "shape_type": "point",
      "flags": {},
      "mask": null
    },
    {
      "label": "car",
      "points": [
        [
          45.15,
          91.26
        ]
      ],
      "group_id": null,
      "description": "",
      "shape_type": "point",
      "flags": {},
      "mask": null
    },
    {
      "label": "motorbike",
      "points": [
        [
          164.53,
          92.59
        ]
      ],
      "group_id": null,
      "description": "",
      "shape_type": "point",
      "flags": {},
      "mask": null
    },
    {
      "label": "car",
      "points": [
        [
          453.26,
          101.62
        ]
      ],
      "group_id": null,
      "description": "",
      "shape_type": "point",
      "flags": {},
      "mask": null
    },
    {
      "label": "motorbike",
      "points": [
        [
          257.07,
          102.33
        ]
      ],
      "group_id": null,
      "description": "",
      "shape_type": "point",
      "flags": {},
      "mask": null
    },
    {
      "label": "car",
      "points": [
        [
          394.3,
          104.13
        ]
      ],
      "group_id": null,
      "description": "",
      "shape_type": "point",
      "flags": {},
      "mask": null
    },
    {
      "label": "motorbike",
      "points": [
        [
          93.12,
          106.89
        ]
      ],
      "group_id": null,
      "description": "",
      "shape_type": "point",
      "flags": {},
      "mask": null
    },
    {
      "label": "motorbike",
      "points": [
        [
          369.14,
          112.87
        ]
      ],
      "group_id": null,
      "description": "",
      "shape_type": "point",
      "flags": {},
      "mask": null
    },
    {
      "label": "car",
      "points": [
        [
          300.87,
          116.51
        ]
      ],
      "group_id": null,
      "description": "",
      "shape_type": "point",
      "flags": {},
      "mask": null
    },
    {
      "label": "car",
      "points": [
        [
          9.71,
          133.61
        ]
      ],
      "group_id": null,
      "description": "",
      "shape_type": "point",
      "flags": {},
      "mask": null
    },
    {
      "label": "motorbike",
      "points": [
        [
          405.55,
          142.61
        ]
      ],
      "group_id": null,
      "description": "",
      "shape_type": "point",
      "flags": {},
      "mask": null
    },
    {
      "label": "car",
      "points": [
        [
          78.48,
          237.31
        ]
      ],
      "group_id": null,
      "description": "",
      "shape_type": "point",
      "flags": {},
      "mask": null
    },
    {
      "label": "motorbike",
      "points": [
        [
          229.02,
          257.2
        ]
      ],
      "group_id": null,
      "description": "",
      "shape_type": "point",
      "flags": {},
      "mask": null
    },
    {
      "label": "car",
      "points": [
        [
          118.6,
          268.23
        ]
      ],
      "group_id": null,
      "description": "",
      "shape_type": "point",
      "flags": {},
      "mask": null
    },
    {
      "label": "motorbike",
      "points": [
        [
          188.69,
          277.35
        ]
      ],
      "group_id": null,
      "description": "",
      "shape_type": "point",
      "flags": {},
      "mask": null
    }
  ],
  "imagePath": "20251116_151838_081.jpg",
  "imageData": null,
  "imageHeight": 294,
  "imageWidth": 518
}